pyproject.toml
test_equipment/__init__.py
test_equipment/cm2100b.py
test_equipment/dmm_8112_3.py
test_equipment/psu.py
test_equipment/psu_ctrl.py
test_equipment/serial_helper.py
test_equipment/shelly.py
test_equipment/visa_helper.py
test_equipment-1.1.8.dist-info/METADATA
test_equipment-1.1.8.dist-info/WHEEL
test_equipment-1.1.8.dist-info/entry_points.txt
test_equipment-1.1.8.dist-info/RECORD
