Metadata-Version: 2.1
Name: test-equipment
Version: 1.1.8
Summary: Interfaces to various pieces of test equipment.
Home-page: https://github.com/pjaos/test_equipment
License: MIT
Author: Paul Austen
Author-email: pjaos@gmail.com
Requires-Python: >=3.10,<4.0
Classifier: License :: OSI Approved :: MIT License
Classifier: Programming Language :: Python :: 3
Classifier: Programming Language :: Python :: 3.10
Classifier: Programming Language :: Python :: 3.11
Classifier: Programming Language :: Python :: 3.12
Requires-Dist: bleak
Requires-Dist: p3lib (>=1.1.107,<2.0.0)
Requires-Dist: pymodbus
Requires-Dist: pyserial
Requires-Dist: pyvisa
Requires-Dist: pyvisa-py
Requires-Dist: requests
Project-URL: Repository, https://github.com/pjaos/test_equipment
